momapa/__init__.py
momapa/argument.py
momapa/asset.py
momapa/file.py
momapa/java.py
momapa/library.py
momapa/logging.py
momapa/manifest.py
momapa/os.py
momapa/rule.py
momapa/validator.py
tests/__init__.py
tests/argument_test.py
tests/assetindex_test.py
tests/file_test.py
tests/gamedownloads_test.py
tests/java_version_test.py
tests/rule_test.py
tests/test_library.py
tests/test_logging.py
tests/test_rule_validator.py
tests/test_ruleset_validator.py
momapa-0.2.dist-info/LICENSE.md
momapa-0.2.dist-info/METADATA
momapa-0.2.dist-info/WHEEL
momapa-0.2.dist-info/top_level.txt
momapa-0.2.dist-info/RECORD
